.coverage
CHANGES.txt
MANIFEST.in
README.txt
development.ini
production.ini
pyramid.wsgi
setup.cfg
setup.py
html/api-objects.txt
html/class-tree.html
html/crarr.png
html/epydoc.css
html/epydoc.js
html/exceptions.AssertionError-class.html
html/frames.html
html/help.html
html/identifier-index.html
html/index.html
html/module-tree.html
html/redirect.html
html/sapproject-module.html
html/sapproject-pysrc.html
html/sapproject.models-module.html
html/sapproject.models-pysrc.html
html/sapproject.models.base-module.html
html/sapproject.models.base-pysrc.html
html/sapproject.models.permiso-module.html
html/sapproject.models.permiso-pysrc.html
html/sapproject.models.permiso.Permiso-class.html
html/sapproject.models.proyecto-module.html
html/sapproject.models.proyecto-pysrc.html
html/sapproject.models.proyecto.Proyecto-class.html
html/sapproject.models.proyectousuario-module.html
html/sapproject.models.proyectousuario-pysrc.html
html/sapproject.models.proyectousuario.ProyectoUsuario-class.html
html/sapproject.models.proyectousuariorol-module.html
html/sapproject.models.proyectousuariorol-pysrc.html
html/sapproject.models.proyectousuariorol.ProyectoUsuarioRol-class.html
html/sapproject.models.rol-module.html
html/sapproject.models.rol-pysrc.html
html/sapproject.models.rol.Rol-class.html
html/sapproject.models.rolpermiso-module.html
html/sapproject.models.rolpermiso-pysrc.html
html/sapproject.models.rolpermiso.RolPermiso-class.html
html/sapproject.models.rolusuario-module.html
html/sapproject.models.rolusuario-pysrc.html
html/sapproject.models.rolusuario.RolUsuario-class.html
html/sapproject.models.security-module.html
html/sapproject.models.security-pysrc.html
html/sapproject.models.security.rootFactory-module.html
html/sapproject.models.security.rootFactory-pysrc.html
html/sapproject.models.security.rootFactory.RootFactory-class.html
html/sapproject.models.usuario-module.html
html/sapproject.models.usuario-pysrc.html
html/sapproject.models.usuario.Usuario-class.html
sapproject.egg-info/PKG-INFO
sapproject.egg-info/SOURCES.txt
sapproject.egg-info/dependency_links.txt
sapproject.egg-info/entry_points.txt
sapproject.egg-info/not-zip-safe
sapproject.egg-info/requires.txt
sapproject.egg-info/top_level.txt
